splade_index/__init__.py
splade_index/hf.py
splade_index/pytorch.py
splade_index/selection.py
splade_index/stopwords.py
splade_index/version.py
splade_index/numba/__init__.py
splade_index/numba/retrieve_utils.py
splade_index/numba/selection.py
splade_index/utils/__init__.py
splade_index/utils/corpus.py
splade_index/utils/json_functions.py
splade_index-0.2.0.dist-info/licenses/LICENSE
splade_index-0.2.0.dist-info/METADATA
splade_index-0.2.0.dist-info/WHEEL
splade_index-0.2.0.dist-info/top_level.txt
splade_index-0.2.0.dist-info/RECORD
