Metadata-Version: 2.4
Name: splade_index
Version: 0.2.0
Summary: An ultra-fast search index for SPLADE sparse neural retrieval models.
Home-page: https://github.com/rasyosef/splade-index
Author: Yosef Worku Alemneh
Author-email: 
Classifier: Programming Language :: Python :: 3
Classifier: License :: OSI Approved :: MIT License
Classifier: Operating System :: OS Independent
Requires-Python: >=3.9
License-File: LICENSE
Requires-Dist: numpy
Requires-Dist: sentence-transformers>=5.0.0
Provides-Extra: core
Requires-Dist: orjson; extra == "core"
Requires-Dist: tqdm; extra == "core"
Requires-Dist: numba; extra == "core"
Provides-Extra: hf
Requires-Dist: huggingface_hub; extra == "hf"
Provides-Extra: dev
Requires-Dist: black; extra == "dev"
Provides-Extra: selection
Requires-Dist: torch; extra == "selection"
Provides-Extra: evaluation
Requires-Dist: pytrec_eval; extra == "evaluation"
Provides-Extra: full
Requires-Dist: orjson; extra == "full"
Requires-Dist: tqdm; extra == "full"
Requires-Dist: numba; extra == "full"
Requires-Dist: huggingface_hub; extra == "full"
Requires-Dist: black; extra == "full"
Requires-Dist: torch; extra == "full"
Requires-Dist: pytrec_eval; extra == "full"
Dynamic: author
Dynamic: classifier
Dynamic: description
Dynamic: description-content-type
Dynamic: home-page
Dynamic: license-file
Dynamic: provides-extra
Dynamic: requires-dist
Dynamic: requires-python
Dynamic: summary
